LICENSE
MANIFEST.in
README.rst
demo.py
setup.py
tests.py
toradbapi.py
toradbapi.egg-info/PKG-INFO
toradbapi.egg-info/SOURCES.txt
toradbapi.egg-info/dependency_links.txt
toradbapi.egg-info/requires.txt
toradbapi.egg-info/top_level.txt