Metadata-Version: 1.1
Name: toradbapi
Version: 0.1.3
Summary: Wrapper for twisted.enterprise.adbapi.ConnectionPool to use with tornado
Home-page: https://github.com/geerk/toradbapi
Author: Timofey Trukhanov
Author-email: timofey.trukhanov@gmail.com
License: MIT
Platform: UNKNOWN
Classifier: Development Status :: 4 - Beta
Classifier: Intended Audience :: Developers
Classifier: License :: OSI Approved :: MIT License
Classifier: Programming Language :: Python :: Implementation :: CPython
Classifier: Programming Language :: Python :: Implementation :: PyPy
Classifier: Programming Language :: Python :: 2.7
Classifier: Operating System :: OS Independent
Classifier: Topic :: Database
